libname/LKmod.py
libname/__init__.py
LKmod-0.0.10.dist-info/METADATA
LKmod-0.0.10.dist-info/WHEEL
LKmod-0.0.10.dist-info/top_level.txt
LKmod-0.0.10.dist-info/RECORD
