Metadata-Version: 2.1
Name: LKmod
Version: 0.0.10
Summary: lock and key
Home-page: UNKNOWN
Author: UNKNOWN
Author-email: UNKNOWN
License: UNKNOWN
Keywords: python
Platform: UNKNOWN
